tee_tee/__init__.py
tee_tee/main.py
tee_tee-0.1.2.dist-info/entry_points.txt
tee_tee-0.1.2.dist-info/LICENSE
tee_tee-0.1.2.dist-info/WHEEL
tee_tee-0.1.2.dist-info/METADATA
tee_tee-0.1.2.dist-info/RECORD
